Workbook

Sheet 拍摄总表
D1: 订单信息（小拍填）-- 必填 | R1: 定金明细（小拍填） | X1: 渠道市场（小拍填） | AC1: 家人信息（小秘书填） | AN1: 拍摄团队（小秘书填） | AY1: 裂变情况（小秘书填） | BA1: 选片加片（小秘书填） | BF1: 续订情况（小秘书填） | BJ1: 回家另加（小秘书填）
A2: 备注 | B2: 录入人 | C2: 订单编号 | D2: 客户微信名 | E2: 客户姓名 | F2: 手机 | G2: 到店时间 | H2: 拍摄地点 | I2: 套餐名称 | J2: 拍摄对象 | K2: 拍摄内容 | L2: 拍摄时长 | M2: 精修张数 | N2: 未选底片 | O2: 印刷品 | P2: 化妆发型 | Q2: 拍摄心愿 | R2: 定金时间 | S2: 定金金额 | T2: 付款方式 | U2: 套餐金额 | V2: 应付尾款 | W2: 备注 | X2: 介绍人 | Y2: 媒介渠道 | Z2: 参加活动 | AA2: 接单人 | AB2: 类型 | AC2: 大宝姓名 | AD2: 昵称 | AE2: 性别 | AF2: 出生日期 | AG2: 小宝姓名 | AH2: 昵称 | AI2: 性别 | AJ2: 出生日期 | AK2: 其他家人信息 | AL2: 地址 | AM2: 电子邮件 | AN2: 拍摄日期 | AO2: 摄影师 | AP2: 满意度 | AQ2: 化妆师 | AR2: 满意度 | AS2: 引导师/助理 | AT2: 满意度 | AU2: 尾款时间 | AV2: 尾款金额 | AW2: 尾款方式 | AX2: 本单服务金额 | AY2: 是否参加点评活动 | AZ2: 是否发朋友圈 | BA2: 选片人员 | BB2: 付款时间 | BC2: 金额 | BD2: 付款方式 | BE2: 内容 | BF2: 付款时间 | BG2: 续订金额 | BH2: 付款方式 | BI2: 续订内容 | BJ2: 付款时间 | BK2: 金额 | BL2: 付款方式 | BM2: 内容
B3: 丹丹 | C3: S20192001 | D3: 小圆手 | I3: 299台历活动 | S3: 299 | X3: 老客户 | Z3: 台历活动 | AB3: 超低价促销 | AN3: 43454 | AO3: 米加 | AQ3: 无 | AS3: 熊妈 | AU3: / | AV3: 0 | AX3: 299 | BF3: 43456 | BG3: 2880 | BH3: pos | BI3: 2880F
B4: 丹丹 | C4: S20192002 | D4: 咩咩新年照 | Z4: 免费圣诞照 | AB4: 免拍 | AN4: 43463 | AO4: 团子 | AQ4: 明珠 | AS4: 熊妈 | AU4: / | AV4: 0 | AW4: / | AX4: 0
B5: 丹丹 | C5: S20192003 | D5: 两人哺乳照 | AA5: 其他 | AB5: 免拍 | AN5: 43593 | AO5: / | AQ5: / | AS5: / | AU5: / | AV5: / | AW5: / | AX5: / | BF5: 43605 | BG5: 1500 | BH5: pos和支付宝 | BI5: 2880F
B6: 丹丹 | C6: S20192004 | D6: 邓小邓加印刷 | AN6: 43653 | BJ6: 43696 | BK6: 234 | BL6: 支付宝 | BM6: 加印刷
B7: 丹丹 | C7: S20192005 | D7: tinyhands拍摄 | AB7: 其他（活动外拍） | AN7: 43663 | AO7: 立衡/之一 | AQ7: / | AS7: 熊妈 | AU7: 43713 | AV7: 3000 | AW7: 上海银行 | AX7: 3000
B8: 祖祖 | C8: S20192006 | D8: Jihui Zhang | I8: 149证件照 | V8: 134 | AA8: Yuki | AB8: 超低价促销 | AN8: 43806 | AO8: 米加 | AQ8: / | AS8: / | AU8: 43806 | AV8: 134 | AW8: pos | AX8: 134
B9: 祖祖 | C9: S20192007 | D9: CC.JC | I9: 99证件照 | V9: 99 | X9: 老客户 | AA9: Yuki | AB9: 正价 | AN9: 43807 | AO9: 米加 | AQ9: / | AS9: 果冻 | AU9: 43807 | AV9: 99 | AW9: pos | AX9: 99
A10: y | B10: 丹丹 | C10: S20192008 | D10: athena | Z10: ？ | AN10: / | BB10: 43469 | BC10: 240 | BD10: 微信 | BE10: 加精修
B11: 祖祖 | C11: S20192009 | D11: 双 | E11: 吕小姐 | F11: 13816125386 | G11: 未定 | I11: 4480定制 | V11: 4032 | X11: 老客户 | AB11: 正价折扣
B12: 祖祖 | C12: S20192010 | D12: 毛阿毛 | I12: 1080F | X12: 老客户 | AN12: 43827 | AO12: 团子 | AQ12: / | AS12: 小茹/胡清 | AU12: 43827 | AV12: 1080 | AW12: pos | AX12: 1080
B13: 祖祖 | C13: S20192011 | D13: 陆应 | E13: / | F13: 18321718075 | G13: 未定 | H13: 古羊路158号 | I13: 1000职业照 | J13: 个人 | K13: 1套职业照 | L13: 1小时 | M13: 3张 | N13: 不包含 | O13: 不包含 | P13: 包含 | Q13: 多拍几张全身 | R13: 43814 | S13: 500 | T13: 微信 | U13: 1000 | V13: 500 | W13: 朋友推荐 | X13: 张慧 | Z13: 无 | AA13: Yuki | AB13: 正价 | AN13: 43834 | AO13: 立衡
B14: Yuki | C14: S20192012 | D14: Alice | E14: / | F14: 18611970187 | G14: 2020-12月 | H14: Steps四袋拍摄影棚内 | I14: 4480主题定制 | J14: Winston（2017.11.25弟弟）+Wilson（2013.2.7哥哥）+爸爸妈妈 | K14: 宝宝单人照2组，全家福1组 | L14: 2-3小时 | M14: 20 | N14: 全送 | O14: 10寸轻相册一本 | P14: 提供 | Q14: 妈妈拍好看，单人照哥哥和弟弟各一组。 | R14: 43814 | S14: 2000 | T14: 支付宝500+现金1500 | U14: 4480 | V14: 2480 | W14: 老客户续约，拍摄时间暂定12月左右，提前一个月确认具体时间 | X14: 老客户 | Y14: 续订 | AA14: Yuki | AB14: 正价
A15: 已打印 | B15: Yuki | C15: S20192013 | D15: yanghx | E15: 杨女士 | F15: 13774245131 | G15: 2020.1.1 10:00:00 | H15: Steps四袋拍摄影棚内 | I15: 3680亲子+儿童 | J15: 可可（2019.1.12妹妹）+哥哥+爸爸妈妈 | K15: 宝宝单人照1组，全家福1组 | L15: 2-3小时 | M15: 18 | N15: 全送 | O15: 8寸萝莉册 | P15: 提供 | Q15: 套餐先待定3680，沟通过风格后可更换其他套餐 | R15: 43815 | S15: 500 | T15: 微信 | U15: 3680 | V15: 3180 | W15: 全家福哥哥免费出镜，另外再拍点哥哥和妹妹的合影 | Y15: 点评 | AA15: Yuki | AB15: 正价 | AN15: 43831 | AO15: 米加 | AQ15: 10 | AS15: 陈晓 | AU15: 43831 | AV15: 3180 | AW15: pos | AX15: 3680
B16: Yuki | C16: S20192014 | D16: ultraman | E16: 韩晓晨 | F16: 13701920221 | G16: 2020.3月-2021.3月 | H16: Steps四袋拍摄影棚内 | I16: 2980儿童肖像 | J16: 小太阳（2019.3.22男孩） | K16: 宝宝单人照2组 | L16: 2小时左右 | M16: 16 | N16: 全送 | O16: 20寸油画框 | P16: 提供 | Q16: 套餐可转闺蜜照，如果闺蜜照只拍1组价格可按照2980个人self的基础上额外增加500/人，另外多2张精修的费用算，如果拍宝宝单人照或者全家福可在2年左右拍完。 | R16: 43815 | S16: 2480 | T16: pos | U16: 2480 | V16: 0 | W16: 老客户续约，套餐暂定2480，后期可更换其他正价套餐。 | X16: 御姐萌妹 | Y16: 续订 | AA16: Yuki | AB16: 平日特惠
B17: Yuki | C17: S20192015 | D17: mich | E17: 朱一菡 | F17: 13632223176 | G17: 2020.9月左右 | H17: Steps四袋拍摄影棚内 | I17: 2880全家福 | J17: 弟弟（2019.9.3）+暖暖（2015.12.23姐姐）+爸爸妈妈 | K17: 棚内家庭照1组 | L17: 2小时左右 | M17: 12 | N17: 全送 | O17: 20寸油画框 | P17: 提供 | Q17: 弟弟单人照和姐姐单人照都拍一点 | R17: 43815 | S17: 2880 | T17: pos | U17: 2880 | V17: 0 | W17: 老客户续约，拍摄时间暂定弟弟9月生日前后。 | X17: 老客户 | Y17: 续订 | AA17: Yuki | AB17: 正价
A18: 已打印 | B18: Yuki | C18: S20192016 | D18: 团子 | E18: 葛晓滢 | F18: 13524455895 | G18: 2020.12.22.10：00 | H18: Steps四袋拍摄影棚内 | I18: 4480主题定制 | J18: 兜兜（2019.9.10男孩）+爸爸妈妈+外公外婆 | K18: 宝宝单人照2组，全家福1组 | L18: 2-3小时左右 | M18: 20+4=24张 | N18: 全送 | O18: 10寸轻相册一本 | P18: 提供 | Q18: 棚内有适合兜兜的服装可提供 | R18: 43817 | S18: 500 | T18: 微信 | U18: 4480 | V18: 3980 | W18: 一家三口 | Y18: 点评 | AA18: Yuki | AB18: 正价 | AN18: 43821 | AO18: 米加 | AQ18: 10 | AS18: 果冻/胡清 | AU18: 43821 | AV18: 3980 | AW18: pos | AX18: 4480 | BF18: 43825 | BG18: 1500 | BH18: pos | BI18: 2980儿童肖像
A19: 已打印 | B19: Yuki | C19: S20192017 | D19: hengyi | E19: 18916171988 | F19: 赵恒谊 | G19: 2020.1.11.16：30 | H19: Steps四袋拍摄影棚内 | I19: 5900steps3 | J19: 安康（2019.1.16男孩）+爸爸妈妈+爷爷奶奶 | K19: 棚内2套 | L19: 2-3小时左右 | M19: 15+2=17张 | N19: 全送 | O19: 20寸油画框 | P19: 提供 | Q19: / | R19: / | S19: / | T19: / | U19: 5900steps | V19: 500 | W19: 成长套餐最后一次拍摄。 | X19: 老客户 | AA19: Yuki | AB19: 正价 | AD19: 安康 | AE19: 男 | AF19: 43481
A20: 已打印 | B20: Yuki | C20: S20192018 | D20: 蛋黄小噗噗 | E20: 吴佳琳 | F20: 15026768701 | G20: 43871.417 | H20: Steps四袋拍摄影棚内 | I20: 4480主题定制 | J20: 齐齐（2019.2月男孩）+爸爸妈妈 | K20: 宝宝单人照2组，全家福1组，哺乳照1组。 | L20: 2-3小时左右 | M20: 20+2=22张 | N20: 全送 | O20: 10寸轻相册一本 | P20: 包含 | Q20: 要拍一点抓周照。 | R20: 43817 | S20: 3680 | T20: 点评 | U20: 3680平日特惠 | V20: 0 | W20: 老客户续约，平日拍摄活动折后3680，另外拍1组哺乳照。 | X20: 老客户 | Y20: 续订 | AA20: Yuki | AB20: 正价折扣
B21: Yuki | C21: S20192019 | D21: Karen niu | E21: 牛佳 | F21: 13918116199 | G21: 2020-12月左右 | H21: 黄金城道/新虹桥中心花园 | I21: 1980mini外景 | J21: 11（2012.11.9姐姐）+22（2017.7.7妹妹）+爸爸妈妈 | K21: 家庭照 | L21: 50分钟 | M21: 10 | N21: 全送 | O21: 无 | P21: 自备 | Q21: 可带长辈出镜 | R21: 43817 | S21: 1980 | T21: pos | U21: 1980 | V21: 0 | W21: 老客户续约，拍摄黄金雨或者新虹桥中心花园待定，提前一个月确认。 | X21: 老客户 | Y21: 续订 | AA21: Yuki | AB21: 正价
A22: 已打印 | B22: Yuki | C22: S20192020 | D22: 奶牛宝宝 | E22: 万丽 | F22: 13501720358 | G22: 43826.667 | H22: Steps四袋拍摄影棚内 | I22: 2980全家福+光影 | J22: Mario（2015.4.26弟弟）+姐姐（2013.06.19）+爸爸妈妈 | K22: 家庭照 | L22: 2个小时左右 | M22: 12+1 | N22: 全送 | O22: 20寸油画框 | P22: 提供 | Q22: 全家福风格正常沟通，另外可再拍一组剪影照或者表情包，现场确认。 | R22: 43817 | S22: 500 | T22: 微信 | U22: 2980 | V22: 2480 | W22: 老客户续拍，免费多一人入镜。 | X22: 老客户 | AA22: Yuki | AB22: 正价折扣 | AN22: 43827 | AO22: 立衡 | AQ22: 王婵 | AS22: 果冻/小茹 | AU22: 43827 | AV22: 2480 | AW22: pos | AX22: 2980
A23: 已打印 | B23: Yuki | C23: S20192021 | D23: Richie | E23: 陈周平 | F23: 13816067670 | G23: 43825.562 | H23: Steps四袋拍摄影棚内 | I23: 4480主题定制 | J23: 陈不染（2019.9.15女孩）+爸爸妈妈 | K23: 宝宝单人照2组，全家福1组，哺乳照1组。 | L23: 2-3小时左右 | M23: 20+2=22 | N23: 全送 | O23: 10寸轻相册一本 | P23: 提供 | Q23: 待沟通 | R23: 43818 | S23: 3680 | T23: 点评 | U23: 3680 | V23: 0 | W23: 点评活动，平日拍折后3680。 | Y23: 点评 | AA23: Yuki | AB23: 正价折扣 | AN23: 43825 | AO23: 米加 | AQ23: 10 | AS23: 果冻 | AU23: / | AV23: / | AW23: / | AX23: 3680
B24: Yuki | C24: S20192022 | D24: 不懒了 | E24: 蓝天皓 | F24: 13801951105 | G24: 2020-2月下旬 | H24: Steps四袋拍摄影棚内 | I24: 4480主题定制 | J24: 菜菜（2015.11.28姐姐）+肉肉（2019.11.9妹妹）+爸爸妈妈 | K24: 宝宝单人照2组，全家福1组，哺乳照1组。 | L24: 2-3小时左右 | M24: 20+2=22 | N24: 全送 | O24: 10寸轻相册一本 | P24: 提供 | Q24: 单人照可姐姐妹妹各一组。 | R24: 43818 | S24: 3680 | T24: 点评 | U24: 3680 | V24: 0 | W24: 老客户续拍，平日拍摄套餐折后3680，百日大概2.27号左右，时间暂定百日，最晚周岁前拍摄完成 | X24: 老客户 | Y24: 续订 | AA24: Yuki | AB24: 正价折扣
A25: 已打印 | B25: Yuki | C25: S20192023 | D25: 一蒙 | E25: / | F25: 18117102052 | G25: 44193.417 | H25: Steps四袋拍摄影棚内 | I25: 4880全家福 | J25: 又欢（2014.3.16姐姐）+又乐（2017.1月妹妹）+爸爸妈妈 | K25: 棚内2套 | L25: 2-3小时左右 | M25: 25 | N25: 全送 | O25: 10寸轻相册一本 | P25: 提供 | Q25: 待沟通 | R25: / | S25: 500 | T25: 微信 | U25: 3848 | V25: 3348 | W25: 参加转发活动套系-300，老客户预约新套餐套系85折 | X25: 老客户 | AA25: Yuki | AB25: 正价折扣
B26: Yuki | C26: S20192024 | D26: 阿池池 | E26: 池小姐 | F26: 13918210550 | G26: 2020-11-12月左右 | H26: Steps四袋拍摄影棚内 | I26: 3980外景 | J26: 球球（2016.11.10男孩）+爸爸妈妈 | K26: 家庭照 | L26: 2小时 | M26: 20张 | N26: 全送 | O26: 10寸轻相册一本 20寸油画框一个 | P26: 提供 | Q26: 待沟通 | R26: 43818 | S26: 3580 | T26: 点评 | U26: 3580 | V26: 0 | W26: 老客户续拍，点评活动折后3580。拍摄时间暂定12月左右，提前一个月左右确认时间。拍黄金雨。 | X26: 老客户 | Y26: 续订 | AA26: Yuki | AB26: 正价折扣
A27: 已打印 | B27: Yuki | C27: S20192025 | D27: 周咩咩 | E27: 陆海源 | F27: 18516089280 | G27: 43819.417 | H27: Steps四袋拍摄影棚内 | I27: 1400小主题 | J27: Ollie | K27: 棚内1套宝宝单人 | L27: 1小时左右 | M27: 8 | N27: 不含 | O27: 7寸精致摆台 一个 | P27: 提供 | Q27: 待沟通 | R27: 43818 | S27: 1400 | T27: 微信 | U27: 1400 | V27: 0 | W27: 老客户续拍额外赠送一个摆台。 | X27: 老客户 | AA27: Yuki | AB27: 超低价促销 | AN27: 43819 | AO27: 立衡 | AQ27: 10 | AS27: 果冻 | AU27: / | AV27: / | AW27: / | AX27: 1400 | BF27: 43819 | BG27: 1400
A28: 已打印 | B28: Yuki | C28: S20192026 | D28: 金钥匙 | E28: 曹晓 | F28: 18001783093 | G28: 43820.667 | H28: Steps四袋拍摄影棚内 | I28: 1400小主题 | J28: 兴宝（2013.8.25男孩)+妈妈 | K28: 棚内1套 | L28: 1小时左右 | M28: 8+2=10 | N28: 全送 | O28: 无 | P28: 提供 | Q28: 待沟通 | R28: 43818 | S28: 500 | T28: 微信 | U28: 1400+500=1900 | V28: 1400 | W28: 另外增加妈妈入镜，额外增加500，多2张精修。 | X28: 之一 | AA28: Yuki | AB28: 超低价促销 | AN28: 43820 | AO28: 米加 | AQ28: 10 | AS28: 果冻/小茹 | AU28: 43820 | AV28: 1400 | AW28: pos | AX28: 1900
A29: 已打印 | B29: Yuki | C29: S20192027 | D29: 周公子（danny） | E29: danny | F29: 15800510390 | G29: 43841.417 | H29: Steps四袋拍摄影棚内 | I29: 2880全家福 | J29: 果果（2016.12.06男孩）+妈妈+外公外婆 | K29: 棚内1套 | L29: 2小时左右 | M29: 12 | N29: 全送 | O29: 20寸油画框一个 | P29: 提供 | Q29: 待沟通 | R29: 43819 | S29: 500 | T29: 微信 | U29: 3000 | V29: 2500 | W29: 额外增加一位长辈出镜，增加120，仅限此单。 | X29: / | AA29: Yuki | AB29: 正价
B30: Yuki | C30: S20192028 | D30: 周咩咩 | E30: 陆海源 | F30: 18516089280 | G30: 2020-4月 | H30: Steps四袋拍摄影棚内 | I30: 2980儿童肖像 | J30: Ollie（2016.4.12女孩） | K30: 棚内2套 | L30: 2小时左右 | M30: 16 | N30: 全送 | O30: 20寸油画框一个 | P30: 提供 | Q30: 一套拍油画风，另外一套待定。 | R30: 43819 | S30: 1400 | T30: 微信 | U30: 2480 | V30: 1080 | W30: 平日拍套餐-500，折后2480，拍摄时间4月具体待定。 | X30: 老客户 | Y30: 续订 | AA30: Yuki | AB30: 正价折扣
A31: 已打印 | B31: Yuki | C31: S20192029 | D31: 袁佳 | E31: 袁佳 | F31: 18601702120 | G31: 43821.417 | H31: Steps四袋拍摄影棚内 | I31: 3580孕照 | J31: 袁佳（预产期2月初）+准爸爸 | K31: 棚内2套 | L31: 2-3小时左右 | N31: 全送 | O31: 21寸油画框一个 | P31: 提供 | Q31: 待沟通 | R31: 43819 | S31: 500 | T31: 微信 | U31: 3580 | V31: 3080 | W31: / | X31: / | Y31: 点评 | AA31: Yuki | AB31: 正价 | AN31: 43821 | AO31: 立衡 | AQ31: summer | AS31: 熊妈 | AU31: 43821 | AV31: 3080 | AW31: pos | AX31: 3580 | BF31: 43826 | BG31: 3300
A32: 已打印 | B32: Yuki | C32: S20192030 | D32: 橙非比 Phoebe | E32: 程序 | F32: 13661662466 | G32: 43825.417 | H32: Steps四袋拍摄影棚内 | I32: 2980全家福+光影 | J32: 米多多（2014.9月女孩）+爸爸妈妈+外公外婆 | K32: 全家福1组，光影/表情包1组。 | L32: 2小时左右 | M32: 12+1+4=17张 | N32: 全送 | O32: 20寸油画框一个 | P32: 提供 | Q32: 想拍油画风 | R32: 43819 | S32: 2980 | T32: 点评 | U32: 3980 | V32: 1000 | W32: 额外增加外公外婆出镜，多1000出镜费用，多4张精修。 | X32: / | AA32: Yuki | AB32: 正价折扣
A33: 已打印 | B33: Yuki | C33: S20192031 | D33: 栗子 | E33: 刘玮玮 | F33: 13564339618 | G33: 43834.562 | H33: Steps四袋拍摄影棚内 | I33: 2880全家福 | J33: 窈窈（201512女孩）+爸爸妈妈 | K33: 棚内1套 | L33: 2小时左右 | M33: 12+3=15 | N33: 全送 | O33: 绒面桌摆 | P33: 提供 | Q33: 待沟通 | R33: 43819 | S33: 500 | T33: / | U33: 2880 | V33: 2380 | W33: 拍摄1组，团子推荐额外赠送一个绒面小桌摆，原套餐相框不要换3张精修。 | X33: / | AA33: Yuki | AB33: 正价
A34: 已打印 | B34: Yuki | C34: S20192032 | D34: KoKi | E34: 胡琪 | F34: 15618012875 | G34: 43821.562 | H34: Steps四袋拍摄影棚内 | I34: 2980儿童肖像 | J34: Lucas（2015.1.27男孩）+爸爸妈妈 | K34: 全家福1组，光影 | L34: 2小时左右 | M34: 12+1=13 | N34: 全送 | O34: 20寸油画框一个 | P34: 提供 | Q34: 待沟通 | R34: 43821 | S34: 2980 | T34: 点评 | U34: 2980 | V34: 0 | W34: 点评活动，平日拍2980，特殊安排周末。 | X34: 点评 | AA34: Yuki | AB34: 正价折扣 | AN34: 43821 | AO34: 立衡 | AQ34: 胡悠 | AS34: 熊妈 | AU34: / | AV34: / | AW34: / | AX34: 2980
B35: Yuki | C35: S20192033 | D35: 罗斯玛丽朱小妹 | E35: / | F35: 18018667505 | G35: 2020-4-5月 | H35: Steps四袋拍摄影棚内 | I35: 待定 | J35: 晞晞（2012.3.3姐姐）+翰翰（2018.1.30弟弟）+待定 | K35: 待定 | L35: 待定 | M35: 待定 | N35: 待定 | O35: 待定 | P35: 提供 | Q35: 待沟通 | R35: 43821 | S35: 500 | T35: / | U35: 待定 | V35: / | W35: 圣诞照续约，预付500定金，套餐待定，提前微信确认。 | X35: 老客户 | AA35: Yuki
A36: 已打印 | B36: Yuki | C36: S20192034 | D36: 朱婧 | E36: / | F36: 15221391157 | G36: 43834.396 | H36: Steps四袋拍摄影棚内 | I36: 4990每年全家福 | J36: 祎祎（2017.1.11女孩）+爸爸妈妈 | K36: 棚内2套 | L36: 2-3小时左右 | M36: 14 | N36: 全送 | O36: 20寸油画框一个 | P36: 提供 | Q36: 待沟通 | R36: / | S36: / | T36: / | U36: / | V36: / | W36: 成长套餐第二次 | X36: 老客户 | AA36: Yuki | AB36: 正价 | AD36: 祎祎 | AE36: 女 | AF36: 42746
A37: 已打印 | B37: Yuki | C37: S20192035 | D37: 高书恒 | E37: 高书恒 | F37: 15370119812 | G37: 43848.417 | H37: Steps四袋拍摄影棚内 | I37: 2020新年照 | J37: 阳阳（2015.09.11哥哥）+沐沐（2018.04.04弟弟）+爸爸妈妈 | K37: 棚内1套 | L37: 2小时左右 | M37: 6+2=8 | N37: 无 | O37: 7寸精致摆台 一个 | P37: 提供 | Q37: 拍新年照，哥哥120弟弟90，80/110也可以穿 | R37: 43821 | S37: 500 | T37: 微信 | U37: 2020+500=2520 | V37: 2020 | W37: / | AA37: Yuki | AB37: 超低价促销
B38: Yuki | C38: S20192036 | D38: 胖雪闹闹 | E38: 吴姝丽 | F38: 15902145929 | G38: 2020-12月 | H38: Steps四袋拍摄影棚内 | I38: 2880F | J38: 晓晓（2018.12.11女孩）+爸爸妈妈 | K38: 棚内1套 | L38: 2小时左右 | M38: 12 | N38: 全送 | O38: 20寸油画框一个 | P38: 提供 | Q38: 待沟通 | R38: 43821 | S38: 2880 | T38: POS | U38: 2880 | V38: 0 | W38: 周岁照续约，套餐暂定2880，提前一个月确定拍摄时间和套餐，风格待定。 | X38: 老客户 | Y38: 续订 | AA38: Yuki | AB38: 正价
A39: 已打印 | B39: Yuki | C39: S20192037 | D39: 茗芳 | E39: 单女士 | F39: 13524497723 | G39: 43827.667 | H39: Steps四袋拍摄影棚内 | I39: 2020新年照 | J39: 蟠蟠2012.12.6男孩）+爸爸妈妈 | K39: 棚内1套 | L39: 2小时左右 | M39: 6+2=8 | N39: 无 | O39: 7寸精致摆台 一个 | P39: 提供 | Q39: 待沟通 | R39: 43822 | S39: 500 | T39: 微信 | U39: 2020 | V39: 1520 | W39: 之一同学妈妈推荐，额外多送2张精修。 | X39: 金钥匙 | AA39: Yuki | AB39: 超低价促销 | AN39: 43827 | AO39: 米加 | AQ39: 10 | AS39: 小茹/阿哲 | AU39: 43827 | AV39: 1520 | AW39: pos | AX39: 2020
A40: 已打印 | B40: Yuki | C40: S20192038 | D40: 尤嘉 | E40: 尤嘉 | F40: 19822798256 | G40: 43825.417 | H40: Steps四袋拍摄影棚内 | I40: 8880成长2次 | J40: 钖钖（2015.7.13哥哥）+阿端（2016.4.1弟弟） | K40: 棚内2套 | L40: 2-3小时左右 | M40: 25 | N40: 全送 | O40: 10寸轻相册一本 40寸相框 一个 | P40: 提供 | Q40: 待沟通 | R40: / | S40: / | T40: / | U40: 8000 | V40: 0 | W40: 产品相框要不要做选照片时确认，成长第一次。 | X40: 老客户 | AA40: Yuki | AB40: 正价 | AN40: 43825 | AO40: 团子 | AQ40: 10 | AS40: 果冻/熊妈 | AU40: / | AV40: / | AW40: / | AX40: 4000
A41: 已打印 | B41: Yuki | C41: S20192039 | D41: Sabrina | E41: 任湘怡 | F41: 13801686729 | G41: 43863.562 | H41: Steps四袋拍摄影棚内 | I41: 2880F | J41: 格格（2012.2.7女孩）+爸爸妈妈 | K41: 棚内1套 | L41: 2小时左右 | M41: 12+3=15 | N41: 全送 | O41: 无 | P41: 提供 | Q41: 希望化妆化得自然一点，妆感淡一点， | R41: 43822 | S41: 500 | T41: 微信 | U41: 2880 | V41: 2380 | W41: 原套餐内20寸油画框不要换3张精修 | X41: 老客户 | AA41: Yuki | AB41: 正价
B42: Yuki | C42: S20192041 | D42: grace | E42: 郑艳华 | F42: / | G42: 2021-1月 | H42: Steps四袋拍摄影棚内 | I42: 2980儿童肖像 | J42: 毛毛（2019.1.10男孩） | K42: 棚内2套 | L42: 2小时左右 | M42: 16 | N42: 全送 | O42: 20寸油画框一个 | P42: 提供 | Q42: 待沟通 | R42: 43822 | S42: 2480 | T42: POS | U42: 2480 | V42: 0 | W42: 周岁照续约，套餐暂定2980儿童肖像，平日拍折后2480，拍摄前具体确认需不需要更换套餐，时间暂定1月。 | X42: 老客户 | Y42: 续订 | AA42: Yuki | AB42: 正价折扣
A43: 已打印 | B43: Yuki | C43: S20192043 | D43: Ro | E43: 王芸卿 | F43: 15000690018 | G43: 43836.417 | H43: Steps四袋拍摄影棚内 | I43: 2980平日特惠 | J43: 萌萌（2018.1.25女孩）+爸爸妈妈 | K43: 全家福1组，表情包1组。 | L43: 2小时左右 | M43: 13张 | N43: 全送 | O43: 20寸油画框一个 | P43: 提供 | Q43: 待沟通 | R43: 43823 | S43: 2980 | T43: 点评 | U43: 2980 | V43: 0 | W43: 点评活动，平日拍摄特惠2980。 | X43: 点评 | Y43: 点评 | Z43: / | AA43: Yuki | AB43: 正价折扣
B44: Yuki | C44: S20192044 | D44: Pinpinpop | E44: 周霞 | F44: 18221033195 | G44: 43836.396 | H44: Steps四袋拍摄影棚内 | I44: 2980平日特惠 | J44: 照清（2017.7.17男孩）+爸爸妈妈 | K44: 全家福1组，表情包1组。 | L44: 2小时左右 | M44: 12+1+3=16张 | N44: 全送 | O44: 8寸相册 一本 | P44: 提供 | Q44: 全家福选新年主题；加拍一张宝宝的证件照 | R44: 43823 | S44: 2980 | T44: 点评 | U44: 2980 | V44: 0 | W44: 可能再带一位长辈；拍完写点评免费送宝宝证件照 | X44: 老客户 | Z44: / | AA44: Yuki | AB44: 正价折扣
A45: 已打印 | B45: Yuki | C45: S20192045 | D45: 雪梅 | E45: 张雪梅 | F45: 13764947805 | G45: 43835.417 | H45: Steps四袋拍摄影棚内 | I45: 2980self | J45: 雪梅（30岁） | K45: 单人肖像2套 | L45: 2-3小时 | M45: 10张 | N45: 全送 | O45: 8寸precious相框1个 | P45: 提供 | Q45: 30岁留念 | R45: 43823 | S45: 3500 | X45: 老客户 | Z45: / | AA45: Yuki | AB45: 正价折扣
A46: 已打印 | B46: Yuki | C46: S20192046 | D46: sue | E46: 金聪颖 | F46: 13641935971 | G46: 43834.562 | H46: Steps四袋拍摄影棚内 | I46: 3680亲子+儿童 | J46: Lucy（2018.2女孩）+爸爸妈妈 | K46: 全家福1组，宝宝单人照1组。 | L46: 2-3小时 | M46: 18+3=21 | N46: 全送 | O46: 8寸萝莉册 一本 | P46: 提供 | Q46: 待沟通 | R46: 43823 | S46: 500 | T46: 支付宝 | U46: 3312 | V46: 2812 | W46: 老客户续拍套餐9折，仅限此单。 | X46: 老客户 | Z46: / | AA46: Yuki | AB46: 正价折扣
A47: 已打印 | B47: Yuki | C47: S20192047 | D47: 好姑娘vs女流氓 | E47: 岑怿裴 | F47: 13564303414 | G47: 43883.417 | H47: Steps四袋拍摄影棚内 | I47: 2880F | J47: 佳佳（2016.1.13女孩）+爸爸妈妈 | K47: 全家福1组，宝宝单人照1组。 | L47: 2-3小时 | M47: 12 | N47: 全送 | O47: 20寸油画框一个 | P47: 提供 | Q47: 待沟通 | R47: 43824 | S47: 500 | T47: 支付宝 | U47: 2880 | V47: 2380 | W47: 团子的朋友，额外多给宝宝拍1组单人照。 | X47: 团子 | Z47: / | AA47: Yuki | AB47: 正价
A48: 已打印 | B48: Yuki | C48: S20192048 | D48: 吴丹翔 | E48: 吴丹翔 | F48: 18616351660 | G48: 43832.417 | H48: Steps四袋拍摄影棚内 | I48: 2020新年照 | J48: 煦煦（2016.1哥哥）+阿琪（2018.9妹妹）+爸爸妈妈+爷爷奶奶外公外婆 | K48: 棚内1套 | L48: 2-3小时 | M48: 6+8=14 | N48: 无 | O48: 7寸精致摆台 一个 | P48: 提供 | Q48: 待沟通 | R48: 43824 | S48: 500 | T48: 微信 | U48: 4020 | V48: 3520 | W48: 之一朋友，免费多1人出镜，另外4人额外增加500/人的费用，多8张精修。套餐待定4020，拍摄当天确认要不要改4880大家庭套餐。 | X48: 之一 | Z48: / | AA48: Yuki | AB48: 正价折扣
A49: 已打印 | B49: Yuki | C49: S20192049 | D49: yan | E49: 陆小姐 | F49: 13816395610 | G49: 43835.562 | H49: Steps四袋拍摄影棚内 | I49: 2880F | J49: Chloe(2016.7.15 女)Celine(2011.4.16女) Tom(2009.9.16男)+爸爸妈妈 | K49: 棚内1套 | L49: 2-3小时 | M49: 12 | N49: 全送 | O49: 20寸油画框一个 | P49: 提供 | Q49: 待沟通 | R49: / | S49: 699 | T49: / | U49: 2880 | V49: 2181 | W49: 原定699套餐，更换699套餐，多2人入镜。 | X49: 老客户 | Z49: / | AA49: Yuki | AB49: 正价
A50: 已打印 | B50: Yuki | C50: S20192050 | D50: StaroO | E50: 邢亚星 | F50: 15601895753 | G50: 43866.521 | H50: Steps四袋拍摄影棚内 | I50: 4480主题定制 | J50: 小朵拉（2019.02.27女孩）+爸爸妈妈 | K50: 孩子单人照2组，全家福1组，哺乳照1组。 | L50: 2-3小时 | M50: 20+2=22 | N50: 全送 | O50: 10寸轻相册一本 | P50: 提供 | Q50: 待沟通 | R50: 43824 | S50: 3680 | T50: 点评 | U50: 3680 | V50: 0 | W50: 点评活动平日拍摄折后3680。 | X50: 小红书 | Y50: 小红书 | Z50: / | AA50: Yuki | AB50: 正价折扣
B51: 祖祖 | C51: S20192051 | D51: Irene Wang | E51: 汪沁懿 | F51: 18018671749 | H51: Steps四袋拍摄影棚内 | I51: 2980self | R51: 43409 | S51: 500 | T51: 支付宝 | V51: 2480 | X51: 老客户 | Z51: 正价 | AB51: 正价 | AD51: 鼓鼓 | AE51: 男 | AF51: 43008 | AN51: 43824 | AO51: 团子 | AQ51: 10 | AS51: 熊妈/果冻 | AU51: 43824 | AV51: 1924.5 | AW51: 微信/支付宝 | AX51: 2424.5
B52: 之一 | C52: S20192052 | D52: RRT | E52: jorin zhou | F52: 15800921760 | G52: 待定 | H52: Steps四袋拍摄影棚内 | I52: 2880F+1080表情包 | J52: 哩哩（2016.11.20 女孩） | K52: 2套家庭照 | L52: 3小时 | M52: 13 | N52: 全送 | O52: 20寸油画框 | P52: 包含 | R52: 43737 | S52: 2980 | T52: 大众点评团购 | V52: / | X52: 大众点评 | Y52: 大众点评 | AA52: Yuki | AB52: 正价折扣
B53: 之一 | C53: S20192053 | D53: 森小蝶 | E53: 李之晶 | F53: 13761750895 | G53: 未定 | H53: Steps四袋拍摄影棚内 | I53: 6880两次 | R53: 43728 | S53: 500 | T53: pos | V53: / | X53: KOL-Miki | Y53: 朋友圈 | Z53: / | AA53: 丹丹 | AB53: 正价折扣
B54: 之一 | C54: S20192054 | D54: 李晓鸥 | E54: 李晓鸥 | F54: 13816598567 | G54: 待定 | H54: Steps四袋拍摄影棚内 | I54: 2880F | J54: Leo（2012.1.13男孩）+妈妈 | K54: 1套家庭照，1套孩子单人照 | L54: 2-3小时 | M54: 20 | N54: 全送 | O54: 20寸油画框一个 | P54: 包含 | Q54: 待沟通 | R54: 43790 | S54: 2880 | T54: POS | U54: 2880 | V54: 0 | W54: 老客户续订，多送一个1400小主题，仅限此单 | X54: 老客户 | Y54: 续订 | AA54: Yuki | AB54: 正价折扣 | AD54: Leo | AE54: 男 | AF54: 2012.1.13
B55: Yuki | C55: S20192055 | D55: 雪梅 | E55: 张雪梅 | F55: 13764947805 | G55: 待定 | H55: Steps四袋拍摄影棚内 | I55: 2980平日特惠 | J55: 汤圆（2017.02.07男孩） | K55: 棚内2组 | L55: 2小时左右 | M55: 16 | N55: 全送 | O55: 8寸相册 一本 | P55: 提供 | Q55: 待沟通 | R55: 43824 | S55: 500 | T55: 微信 | U55: 2480 | V55: 1980 | W55: 两个套餐一起约，平日价格 可安排周末拍摄。 | X55: 老客户 | AA55: Yuki | AB55: 正价折扣
B56: Yuki | C56: S20192056 | D56: Maggie | E56: 祝颖 | F56: 13916594158 | G56: 43835.667 | H56: Steps四袋拍摄影棚内 | I56: 3980F | J56: 瑞瑞（2016.12.29女孩）+爸爸妈妈 | K56: 棚内2组 | L56: 2-3小时 | M56: 18 | N56: 全送 | O56: 10寸轻相册一本 | P56: 提供 | Q56: 待沟通 | R56: 43824 | S56: 500 | T56: 支付宝 | U56: 3980 | V56: 3480 | W56: 老客户续拍。 | X56: 老客户 | AA56: Yuki | AB56: 正价
B57: Yuki | C57: S20192057 | D57: 沄 | E57: 江润芸 | F57: 13817207116 | G57: 43843.417 | H57: Steps四袋拍摄影棚内 | I57: 2980平日特惠 | J57: 杨杨（2017.1.14男孩）+爸爸妈妈 | K57: 全家福1组，表情包1组。 | L57: 2小时左右 | M57: 12+1=13 | N57: 全送 | O57: 20寸油画框一个 | P57: 提供 | Q57: 待沟通 | R57: 43824 | S57: 2980 | T57: 点评 | U57: 2980 | V57: 0 | W57: 点评活动，平日拍摄特惠2980。 | AA57: Yuki | AB57: 正价折扣
B58: Yuki | C58: S20192058 | D58: 葫芦娃 | E58: 曲霞 | F58: 18930838018 | G58: 2020-待定 | H58: Steps四袋拍摄影棚内 | I58: 2880F | J58: 姐姐（12岁）+妹妹（6岁）+爸爸妈妈 | K58: 棚内1套 | L58: 2小时左右 | M58: 12 | N58: 全送 | O58: 20寸油画框一个 | P58: 提供 | Q58: 待沟通 | R58: 43824 | S58: 2880 | T58: 微信 | U58: 2880 | V58: 0 | W58: 老客户续拍，免费多一人出镜，拍摄时间待定。 | X58: 老客户 | AA58: Yuki | AB58: 正价
B59: Yuki | C59: S20192059 | D59: 团子 | E59: 葛晓滢 | F59: 13524455895 | G59: 2020-9月 | H59: Steps四袋拍摄影棚内 | I59: 2980儿童肖像 | J59: 兜兜（2019.9.10男孩） | K59: 棚内2组 | L59: 2小时左右 | M59: 16 | N59: 全送 | O59: 20寸油画框一个 | P59: 提供 | Q59: 待沟通 | R59: 43825 | S59: 1500 | T59: pos | U59: 2980 | V59: 1480 | W59: 套餐待定宝宝个人照，拍摄前确认，预付1500定金。 | X59: 老客户 | Y59: 续订 | AA59: Yuki | AB59: 正价
B60: Yuki | C60: S20192060 | D60: weihong | E60: 魏红 | F60: 13764626195 | G60: 43849.417 | H60: Steps四袋拍摄影棚内 | I60: 2880F | J60: 张嘉怡（2012.10姐姐）+张佩霖（2016.4弟弟）+爸爸妈妈 | K60: 棚内1套 | L60: 2小时左右 | M60: 12 | N60: 全送 | O60: 20寸油画框一个 | P60: 提供 | Q60: 想拍新年照风格 | R60: 43825 | S60: 500 | T60: 微信 | U60: 2304 | V60: 1804 | W60: 之一朋友，套餐8折，免费多1人入镜。 | X60: 老客户 | AA60: Yuki | AB60: 正价折扣
B61: 祖祖 | C61: S20192061 | D61: 桉树柠檬 | I61: 圣诞+新年样片 | AN61: 43821 | AO61: 团子 | AQ61: 10 | AS61: 果冻 | AU61: / | AV61: / | AW61: / | AX61: /
A62: 已打印 | B62: Yuki | C62: S20192062 | D62: nicongai | E62: 倪雯娇 | F62: 13918852376 | G62: 43828.562 | H62: Steps四袋拍摄影棚内 | I62: 880哺乳照 | J62: 一克拉（2019.4月女孩）+妈妈 | K62: 棚内1套 | L62: 1-2小时左右 | M62: 1 | N62: 无 | O62: 无 | P62: 提供 | Q62: 待沟通 | R62: 43825 | S62: 500 | T62: 微信 | U62: 880 | V62: 380 | W62: 先约880，拍摄完确定要不要更换套餐。 | X62: 点评 | AA62: Yuki | AB62: 超低价促销 | AN62: 43828 | AO62: 之一 | AQ62: 王婵 | AS62: 小茹/徐珍 | AU62: 43828 | AV62: 380 | AW62: pos | AX62: 880
A63: 已打印 | B63: Yuki | C63: S20192063 | D63: 君 | E63: 宋小姐 | F63: 13791008517 | G63: 43827.708 | H63: Steps四袋拍摄影棚内 | I63: 1400圣诞照 | J63: 逗逗（2017.7.10男孩） | K63: 棚内1套 | L63: 1小时左右 | M63: 6 | N63: 无 | O63: 7寸精致摆台 一个 | P63: 提供 | Q63: 拍圣诞照 | R63: 43826 | S63: 500 | T63: 微信 | U63: 1400 | V63: 900 | W63: / | X63: 老客户 | AA63: Yuki | AB63: 超低价促销 | AN63: 43827 | AO63: 立衡 | AQ63: / | AS63: 果冻/胡清 | AU63: 43827 | AV63: 900 | AW63: pos | AX63: 1400
B64: Yuki | C64: S20192064 | D64: KoKi | E64: 胡琪 | F64: 15618012875 | G64: 2020-12月 | H64: Steps四袋拍摄影棚内 | I64: 待定 | J64: Lucas（2015.1.27男孩）+爸爸妈妈 | K64: 待定 | L64: 待定 | M64: 待定 | N64: 待定 | O64: 待定 | P64: 提供 | Q64: 待沟通 | R64: 43826 | S64: 500 | T64: pos | U64: 待定 | V64: 待定 | W64: 老客户续拍，预付500定金，拍摄时间暂定2020.12月左右，提前一个月确定时间和套餐 | X64: 老客户 | AA64: Yuki
A65: 已打印 | B65: Yuki | C65: S20192065 | D65: Rachelting | E65: 陈丽婷 | F65: 13916550947 | G65: 43829.583 | H65: Steps四袋拍摄影棚内 | I65: 2880F | J65: 陈丽婷+爸爸妈妈 | K65: 棚内1套 | L65: 1-2小时左右 | M65: 12 | N65: 无 | O65: 7寸精致摆台 一个 | P65: 提供 | Q65: 可拍其他风格 | R65: 43826 | S65: 500 | T65: 微信 | U65: 2880 | V65: 2380 | W65: 套餐待定2020，拍摄当天或选照片的时候确认要不要换2880。 | X65: 点评 | AA65: Yuki | AB65: 超低价促销 | AN65: 43829 | AO65: 米加 | AQ65: summer | AS65: 果冻 | AU65: 43829 | AV65: 2380 | AW65: pos | AX65: 2880
B66: Yuki | C66: S20192066 | D66: 袁佳 | E66: 袁佳 | F66: 18601702120 | G66: 2020-2月左右 | H66: Steps四袋拍摄影棚内 | I66: 2980新生儿 | J66: 宝宝（预产期2月初） | K66: 2套服装 | L66: 2小时左右 | M66: 9 | N66: 全送 | O66: 10寸精致摆台 一个 | P66: 自备 | Q66: 待沟通 | R66: 43826 | S66: / | T66: / | U66: / | V66: / | W66: 孕照续订，约百日照送新生儿上门，家人可以出镜拍一些。 | X66: 老客户 | AA66: Yuki | AB66: 超低价促销
B67: Yuki | C67: S20192067 | D67: 袁佳 | E67: 袁佳 | F67: 18601702120 | G67: 2020-待定 | H67: Steps四袋拍摄影棚内 | I67: 6880孕照+百日 | J67: 宝宝（预产期2月初）+爸爸妈妈 | K67: 孩子单人照2组，全家福1组，对比照1组。 | L67: 2-3小时 | M67: 20+1 | N67: 全送 | O67: 10寸轻相册一本 | P67: 提供 | Q67: 待沟通 | R67: 43826 | S67: 3300 | T67: pos | U67: 3300 | V67: 0 | W67: 孕照续订，约百日照送新生儿上门，额外赠送对比照1组，额外多1张精修。 | X67: 老客户 | Y67: 续订 | AA67: Yuki | AB67: 正价
B68: Yuki | C68: S20192068 | D68: 雷蒙德 | E68: 李衡 | F68: 18621507331 | G68: 43833.562 | H68: Steps四袋拍摄影棚内 | I68: 1000元职业照 | J68: 李衡 | K68: 棚内1套 | L68: 1-2小时左右 | M68: 3 | N68: 无 | O68: 无 | P68: 提供 | Q68: 待沟通 | R68: 43826 | S68: / | T68: / | U68: / | V68: / | W68: 保时捷员工拍摄券，费用已付。 | X68: 保时捷 | AA68: Yuki
B69: Yuki | C69: S20192069 | D69: Kathyyy | E69: 荆小纯 | F69: 15618521998 | G69: 43847.646 | H69: Steps四袋拍摄影棚内 | I69: 2980平日特惠 | J69: 韬韬（2016.1.5男孩）+爸爸妈妈 | K69: 全家福1组，表情包1组。 | L69: 2小时左右 | M69: 12+1=13 | N69: 全送 | O69: 20寸油画框一个 | P69: 提供 | Q69: 待沟通 | R69: 43826 | S69: 2980 | T69: 点评 | U69: 2980 | V69: 0 | W69: 点评活动平日拍折后2980 | AA69: Yuki
B70: 祖祖 | C70: S20192070 | D70: xinhui | E70: 唐欣慧 | F70: 17721253209 | I70: 成长steps3 | AD70: 淇淇 | AE70: 女 | AF70: 43399 | AN70: 43828 | AO70: 团子 | AQ70: 10 | AS70: 果冻 | AU70: / | AV70: / | AW70: / | AX70: 2633
A71: 已打印 | B71: Yuki | C71: S20192071 | D71: 乐乐 | E71: 乐烨 | F71: 13564256360 | G71: 43835.542 | H71: Steps四袋拍摄影棚内 | I71: 3280亲子+哺乳 | J71: 遥遥（2019.7.25女孩）+爸爸妈妈+外公外婆 | K71: 全家福1组，哺乳照1组。 | L71: 2-3小时 | M71: 12+4=16 | N71: 全送 | O71: 20寸油画框一个 | P71: 提供 | Q71: 待沟通 | R71: 43828 | S71: 500 | T71: 微信 | U71: 4280 | V71: 3780 | W71: 额外增加外公外婆出镜，多500/人的费用，多2张精修。 | X71: sam | AA71: Yuki | AB71: 正价
B72: Yuki | C72: S20192072 | D72: 小马驹 | E72: 马韵 | F72: 13917983800 | G72: 2020-2021/12月 | H72: Steps四袋拍摄影棚内 | I72: 2980儿童肖像 | J72: 高期获（2015.1.4男孩） | K72: 棚内2组 | L72: 2小时左右 | M72: 16 | N72: 全送 | O72: 20寸油画框一个 | P72: 提供 | Q72: 待沟通 | R72: 43828 | S72: 2980 | T72: pos | U72: 2980 | V72: 0 | W72: 套餐暂定宝宝单人照，拍摄前确认，2年有效。 | X72: 老客户 | Y72: 续订 | AA72: Yuki | AB72: 正价
A73: 已打印 | B73: Yuki | C73: S20192073 | D73: Becky | E73: 郑伊婷 | F73: 15001889357 | G73: 43829.604 | H73: Steps四袋拍摄影棚内 | I73: 形象照 | J73: 三位老师 | K73: 棚内1套 | L73: 2小时左右 | M73: 每人各一张 | N73: 无 | O73: 无 | P73: 提供 | Q73: 待沟通 | R73: 43826 | S73: 500 | T73: 微信 | U73: 1500 | V73: 1000 | W73: muzika老师，价格500/人，1张精修 | X73: 老客户 | AA73: Yuki | AN73: 43829 | AO73: 立衡 | AQ73: 10/summer | AS73: 熊妈 | AU73: 43829 | AV73: 1000 | AW73: 微信 | AX73: 1500 | BA73: Yuki | BB73: 43829 | BC73: 200 | BD73: pos | BE73: 加精修
A74: 已打印 | B74: Yuki | C74: S20192074 | D74: XtineSoup | E74: 汤储君 | F74: 15921401613 | G74: 43839.562 | H74: Steps四袋拍摄影棚内 | I74: 4480主题定制+1080哺乳照 | J74: 小猪蹄（2019.09.28男孩）+爸爸妈妈+2位长辈 | K74: 孩子单人照1组，全家福1组，哺乳照1组。 | L74: 2-3小时 | M74: 20+2=22 | N74: 全送 | O74: 10寸轻相册一本 | P74: 提供 | Q74: 待沟通 | R74: 43829 | S74: 3680 | T74: pos | U74: 3680 | V74: 0 | W74: 宝宝单人照少拍1组，免费多2位长辈入镜。点评活动平日拍折后3680。 | X74: 点评 | AA74: Yuki | AB74: 正价折扣
A75: 已打印 | B75: Yuki | C75: S20192075 | D75: 惠慧Amy（DG） | E75: 惠慧 | F75: 13040626829 | G75: 43834.396 | H75: Steps四袋拍摄影棚内 | I75: 6980平日大全家福 | J75: 俞嘉浩（2004.08.26男生）+Yu Kawo（2010，9.25男生）+爸爸妈妈 孙文琦（2003.1.22女生）+孙可可（2014.08.26女生）+爸爸妈妈+两位长辈 | K75: 棚内2组 | L75: 3-4小时 | M75: 38 | N75: 全送 | O75: 10寸轻相册 一本 24寸油画框 一个 10寸精致摆台 一个 | P75: 提供 | Q75: 待沟通 | R75: 43829 | S75: 500 | T75: 微信 | U75: 6980 | V75: 6480 | W75: 点评活动平日特惠6980 | X75: Carrie | AA75: Yuki | AB75: 正价折扣
B76: Yuki | C76: S20192076 | D76: Yvonne | E76: 刘佩成 | F76: 18516652770 | G76: 待定 | H76: Steps四袋拍摄影棚内 | I76: 待定 | J76: 预产期4.10日 | K76: 待定 | L76: 待定 | M76: 待定 | N76: 待定 | O76: 待定 | P76: 提供 | Q76: 待沟通 | R76: 43828 | S76: 500 | T76: 微信 | U76: 0 | V76: 0 | AA76: Yuki
B77: Yuki | C77: S20192077 | D77: 君 | E77: 宋小姐 | F77: 13791008517 | G77: 2020/12月 | H77: Steps四袋拍摄影棚内 | I77: 待定 | J77: 逗逗（2017.7.10男孩） | K77: 棚内1套 | L77: 1小时左右 | M77: 待定 | N77: 待定 | O77: 待定 | P77: 提供 | Q77: 拍圣诞照 | R77: 43829 | S77: 500 | T77: pos | U77: 待定 | V77: 待定 | W77: 每年拍圣诞照，套餐暂定1400，如果明年圣诞主题更合算可更换其他套餐，预付500。 | AA77: Yuki
A78: 已打印 | B78: Yuki | C78: S20192078 | D78: Alice.Wang | E78: Alice | F78: 18101882551 | G78: 43863.667 | H78: Steps四袋拍摄影棚内 | I78: 2880F | J78: Selina（200.707.07女孩）+爸爸妈妈 | K78: 棚内1组 | L78: 2小时左右 | M78: 12 | N78: 全送 | O78: 20寸油画框一个 | P78: 提供 | Q78: 待沟通 | R78: 43830 | S78: 500 | T78: 微信 | U78: 2880 | V78: 2380 | W78: / | AA78: Yuki | AB78: 正价
A79: 已打印 | B79: Yuki | C79: S20192079 | D79: 滕小小 | E79: 滕美珠 | F79: 13801831534 | G79: 43843.688 | H79: Steps四袋拍摄影棚内 | I79: 2980儿童肖像 | J79: 张智宸（2011.04.09男孩） | K79: 棚内2组 | L79: 2小时左右 | M79: 16+3=19 | N79: 全送 | O79: 无 | P79: 提供 | Q79: 想拍新年照和小面包师，小朋友身高140。 | R79: 43830 | S79: 2480 | T79: 点评 | U79: 2480 | V79: 0 | W79: 点评活动平日拍折后2480，油画框不要更换3张精修。 | X79: 熊妈 | AA79: Yuki | AB79: 正价折扣
A80: 已打印 | B80: Yuki | C80: S20200001 | D80: pooh的蜂蜜 | E80: 倪惠珏 | F80: 13661627362 | G80: 43876.417 | H80: Steps四袋拍摄影棚内 | I80: 3980F | J80: Emilia（2012.12.23女孩）+爸爸妈妈+CC（金毛）奶酪（柴犬） | K80: 棚内2组 | L80: 2-3小时左右 | M80: 18 | N80: 全送 | O80: 10寸轻相册一本 | P80: 提供 | Q80: 待沟通 | R80: 43831 | S80: 500 | T80: 微信 | U80: 4180 | V80: 3680 | W80: 免费多一直狗狗入镜，另外一只额外总价200入镜费用。给狗狗拍点合影。 | AA80: Yuki | AB80: 正价

Sheet 棚内
B2: 拍摄确认单 | J2: 订单编号 | K2: S20192075
B4: 客户微信名 | D4: =VLOOKUP(K2,拍摄总表!C:Q,2,0) -> 惠慧Amy（DG） | E4: =VLOOKUP(K2,拍摄总表!C:Q,3,0) -> 惠慧 | F4: 手机号 | G4: =VLOOKUP(K2,拍摄总表!C:Q,4,0) -> 13040626829 | J4: 介绍人 | K4: =VLOOKUP(K2,拍摄总表!C:AB,22,0) -> Carrie
B5: 到店时间 | D5: =VLOOKUP(K2,拍摄总表!C:Q,5,0) -> 43834.396 | F5: 拍摄地点 | G5: =VLOOKUP(K2,拍摄总表!C:Q,6,0) -> Steps四袋拍摄影棚内 | J5: 参加活动 | K5: =VLOOKUP(K2,拍摄总表!C:AB,24,0) -> 0
B7: 套餐名称 | D7: =VLOOKUP(K2,拍摄总表!C:Q,7,0) -> 6980平日大全家福 | J7: 摄影师
B8: 拍摄对象 | D8: =VLOOKUP(K2,拍摄总表!C:Q,8,0) -> 俞嘉浩（2004.08.26男生）+Yu Kawo（2010，9.25男生）+爸爸妈妈_x000D_孙文琦（2003.1.22女生）+孙可可（2014.08.26女生）+爸爸妈妈+两位长辈 | J8: 引导/助理
B9: 拍摄内容 | D9: =VLOOKUP(K2,拍摄总表!C:Q,9,0) -> 棚内2组 | J9: 化妆师
B10: 拍摄时长 | D10: =VLOOKUP(K2,拍摄总表!C:Q,10,0) -> 3-4小时
B11: 精修张数 | D11: =VLOOKUP(K2,拍摄总表!C:Q,11,0) -> 38
B12: 未选底片 | D12: =VLOOKUP(K2,拍摄总表!C:Q,12,0) -> 全送
B13: 印刷品 | D13: =VLOOKUP(K2,拍摄总表!C:Q,13,0) -> 10寸轻相册 一本 _x000D_24寸油画框 一个_x000D_10寸精致摆台 一个
B14: 化妆发型 | D14: =VLOOKUP(K2,拍摄总表!C:Q,14,0) -> 提供
B15: 拍摄心愿 | D15: =VLOOKUP(K2,拍摄总表!C:Q,15,0) -> 待沟通
B17: 总金额（元） | D17: =VLOOKUP(K2,拍摄总表!C:AB,19,0) -> 6980 | F17: 尾款（元） | G17: =VLOOKUP(K2,拍摄总表!C:AB,20,0) -> 6480 | H17: （需在拍摄当天付清） | J17: 另加费用
B18: 备注 | D18: =VLOOKUP(K2,拍摄总表!C:AB,21,0) -> 点评活动平日特惠6980
B20: * 关于改期 | D20: 改期费300元（提前7天以上不收改期费）。每一场拍摄团队只服务一组客人，请勿随意改期哦。 | J20: 实收尾款
B21: * 加家人拍摄 | D21: 500元/位，包含妆发，多2张精修
B22: * 加背景及服装 | D22: 1400元/组，精修多6张 | J22: 付款日期
B23: * 另加精修 | D23: 100元/张
B24: * 何时选片 | D24: 拍摄完一周左右 | J24: 付款方式
B25: * 修片&印刷周期 | D25: 修片20天，印刷2周
F26: 客户确认签字
B30: 选片日期 | F30: 选片人 | J30: 选片另加费用
B32: 精修张数 | D32: 张（是否参加点评： 是 / 否 ） | F32: 未修底片 | H32: 张
O33: z
B34: 印刷品 | D34: （颜色、款式、尺寸、照片序号）
B36: 修片要求 | J36: 付款日期
J38: 付款方式
B39: 注： | D39: 由于相框为易碎品，为避免意外，如需发快递只发本市，且24寸以上相框需到店自取。
F40: 客户确认签字

Sheet 哺乳照
B2: 拍摄确认单 | J2: 订单编号 | K2: S20192062
B4: 客户微信名 | D4: =VLOOKUP(K2,拍摄总表!C:Q,2,0) -> nicongai | E4: =VLOOKUP(K2,拍摄总表!C:Q,3,0) -> 倪雯娇 | F4: 手机号 | G4: =VLOOKUP(K2,拍摄总表!C:Q,4,0) -> 13918852376 | J4: 介绍人 | K4: =VLOOKUP(K2,拍摄总表!C:AB,22,0) -> 点评
B5: 到店时间 | D5: =VLOOKUP(K2,拍摄总表!C:Q,5,0) -> 43828.562 | F5: 拍摄地点 | G5: =VLOOKUP(K2,拍摄总表!C:Q,6,0) -> Steps四袋拍摄影棚内 | J5: 参加活动 | K5: =VLOOKUP(K2,拍摄总表!C:AB,24,0) -> 0
B7: 套餐名称 | D7: =VLOOKUP(K2,拍摄总表!C:Q,7,0) -> 880哺乳照 | J7: 摄影师
B8: 拍摄对象 | D8: =VLOOKUP(K2,拍摄总表!C:Q,8,0) -> 一克拉（2019.4月女孩）+妈妈 | J8: 引导/助理
B9: 拍摄内容 | D9: =VLOOKUP(K2,拍摄总表!C:Q,9,0) -> 棚内1套 | J9: 化妆师
B10: 拍摄时长 | D10: =VLOOKUP(K2,拍摄总表!C:Q,10,0) -> 1-2小时左右
B11: 精修张数 | D11: =VLOOKUP(K2,拍摄总表!C:Q,11,0) -> 1
B12: 未选底片 | D12: =VLOOKUP(K2,拍摄总表!C:Q,12,0) -> 无
B13: 印刷品 | D13: =VLOOKUP(K2,拍摄总表!C:Q,13,0) -> 无
B14: 化妆发型 | D14: =VLOOKUP(K2,拍摄总表!C:Q,14,0) -> 提供
B15: 拍摄心愿 | D15: =VLOOKUP(K2,拍摄总表!C:Q,15,0) -> 待沟通
B17: 总金额（元） | D17: =VLOOKUP(K2,拍摄总表!C:AB,19,0) -> 880 | F17: 尾款（元） | G17: =VLOOKUP(K2,拍摄总表!C:AB,20,0) -> 380 | H17: （需在拍摄当天付清） | J17: 另加费用
B18: 备注 | D18: =VLOOKUP(K2,拍摄总表!C:AB,21,0) -> 先约880，拍摄完确定要不要更换套餐。
B20: * 关于改期 | D20: 改期费300元（提前7天以上不收改期费）。每一场拍摄团队只服务一组客人，请勿随意改期哦。 | J20: 实收尾款
B21: * 加家人拍摄 | D21: 500元/位，包含妆发，多2张精修
B22: * 加背景及服装 | D22: 1400元/组，精修多6张 | J22: 付款日期
B23: * 另加精修 | D23: 200元/张
B24: * 何时选片 | D24: 拍摄完一周左右 | J24: 付款方式
B25: * 修片&印刷周期 | D25: 修片1周，印刷2周
F27: 客户确认签字
B31: 选片日期 | F31: 选片人 | J31: 选片另加费用
B33: 精修张数 | D33: 张（是否参加点评： 是 / 否 ） | F33: 未修底片 | H33: 张
O34: z
B35: 印刷品 | D35: （颜色、款式、尺寸、照片序号）
B37: 修片要求 | J37: 付款日期
J39: 付款方式
B40: 注： | D40: 由于相框为易碎品，为避免意外，如需发快递只发本市，且24寸以上相框需到店自取。
F41: 客户确认签字

Sheet 职业照
B2: 拍摄确认单 | J2: 订单编号 | K2: S20192068
B4: 客户微信名 | D4: =VLOOKUP(K2,拍摄总表!C:Q,2,0) -> 雷蒙德 | E4: =VLOOKUP(K2,拍摄总表!C:Q,3,0) -> 李衡 | F4: 手机号 | G4: =VLOOKUP(K2,拍摄总表!C:Q,4,0) -> 18621507331 | J4: 介绍人 | K4: =VLOOKUP(K2,拍摄总表!C:AB,22,0) -> 保时捷
B5: 到店时间 | D5: =VLOOKUP(K2,拍摄总表!C:Q,5,0) -> 43833.562 | F5: 拍摄地点 | G5: =VLOOKUP(K2,拍摄总表!C:Q,6,0) -> Steps四袋拍摄影棚内 | J5: 参加活动 | K5: =VLOOKUP(K2,拍摄总表!C:AB,24,0) -> 0
B7: 套餐名称 | D7: =VLOOKUP(K2,拍摄总表!C:Q,7,0) -> 1000元职业照 | J7: 摄影师
B8: 拍摄对象 | D8: =VLOOKUP(K2,拍摄总表!C:Q,8,0) -> 李衡 | J8: 引导/助理
B9: 拍摄内容 | D9: =VLOOKUP(K2,拍摄总表!C:Q,9,0) -> 棚内1套 | J9: 化妆师
B10: 拍摄时长 | D10: =VLOOKUP(K2,拍摄总表!C:Q,10,0) -> 1-2小时左右
B11: 精修张数 | D11: =VLOOKUP(K2,拍摄总表!C:Q,11,0) -> 3
B12: 未选底片 | D12: =VLOOKUP(K2,拍摄总表!C:Q,12,0) -> 无
B13: 印刷品 | D13: =VLOOKUP(K2,拍摄总表!C:Q,13,0) -> 无
B14: 化妆发型 | D14: =VLOOKUP(K2,拍摄总表!C:Q,14,0) -> 提供
B15: 拍摄心愿 | D15: =VLOOKUP(K2,拍摄总表!C:Q,15,0) -> 待沟通
B17: 总金额（元） | D17: =VLOOKUP(K2,拍摄总表!C:AB,19,0) -> / | F17: 尾款（元） | G17: =VLOOKUP(K2,拍摄总表!C:AB,20,0) -> / | H17: （需在拍摄当天付清） | J17: 另加费用
B18: 备注 | D18: =VLOOKUP(K2,拍摄总表!C:AB,21,0) -> 保时捷员工拍摄券，费用已付。
B20: * 关于改期 | D20: 改期费300元（提前7天以上不收改期费）。每一场拍摄团队只服务一组客人，请勿随意改期哦。 | J20: 实收尾款
B21: * 加团队合影 | D21: 加成员，480元/位，多1张精修。合影精修价格=人数*100元/张
B22: * 加背景及服装 | D22: 1000元/组，精修多3张 | J22: 付款日期
B23: * 另加精修 | D23: 300元/张
B24: * 何时选片 | D24: 拍摄完一周 or 当场选片 | J24: 付款方式
B25: * 修片周期 | D25: 单人套餐：1周；多人团队：20天
F27: 客户确认签字
B31: 选片日期 | F31: 选片人 | J31: 选片另加费用
B33: 精修张数 | D33: 张 | F33: 未修底片 | H33: 张
O34: z
B35: 印刷品 | D35: （颜色、款式、尺寸、照片序号）
B37: 修片要求 | J37: 付款日期
J39: 付款方式
B40: 注： | D40: 由于相框为易碎品，为避免意外，如需发快递只发本市，且24寸以上相框需到店自取。
F41: 客户确认签字

Sheet 外景
B2: 外景 拍摄确认单 | J2: 订单编号
B4: 客户微信名 | D4: =VLOOKUP(K2,拍摄总表!C:Q,2,0) -> #N/A | E4: =VLOOKUP(K2,拍摄总表!C:Q,3,0) -> #N/A | F4: 手机号 | G4: =VLOOKUP(K2,拍摄总表!C:Q,4,0) -> #N/A | J4: 介绍人 | K4: =VLOOKUP(K2,拍摄总表!C:AB,22,0) -> #N/A
B5: 到店时间 | D5: =VLOOKUP(K2,拍摄总表!C:Q,5,0) -> #N/A | F5: 拍摄地点 | G5: =VLOOKUP(K2,拍摄总表!C:Q,6,0) -> #N/A | J5: 参加活动 | K5: =VLOOKUP(K2,拍摄总表!C:AB,24,0) -> #N/A
B7: 套餐名称 | D7: =VLOOKUP(K2,拍摄总表!C:Q,7,0) -> #N/A | J7: 摄影师
B8: 拍摄对象 | D8: =VLOOKUP(K2,拍摄总表!C:Q,8,0) -> #N/A | J8: 引导/助理
B9: 拍摄内容 | D9: =VLOOKUP(K2,拍摄总表!C:Q,9,0) -> #N/A | J9: 化妆师
B10: 拍摄时长 | D10: =VLOOKUP(K2,拍摄总表!C:Q,10,0) -> #N/A
B11: 精修张数 | D11: =VLOOKUP(K2,拍摄总表!C:Q,11,0) -> #N/A
B12: 未选底片 | D12: =VLOOKUP(K2,拍摄总表!C:Q,12,0) -> #N/A
B13: 印刷品 | D13: =VLOOKUP(K2,拍摄总表!C:Q,13,0) -> #N/A
B14: 化妆发型 | D14: =VLOOKUP(K2,拍摄总表!C:Q,14,0) -> #N/A
B15: 拍摄心愿 | D15: =VLOOKUP(K2,拍摄总表!C:Q,15,0) -> #N/A
B17: 总金额（元） | D17: =VLOOKUP(K2,拍摄总表!C:AB,19,0) -> #N/A | F17: 尾款（元） | G17: =VLOOKUP(K2,拍摄总表!C:AB,20,0) -> #N/A | H17: （需在拍摄当天付清） | J17: 另加费用
B18: 备注 | D18: =VLOOKUP(K2,拍摄总表!C:AB,21,0) -> #N/A
B20: * 关于改期 | D20: 改期费300元（提前7天以上不收改期费）。每一场拍摄团队只服务一组客人，请勿随意改期哦。如遇天气不佳，可免费另约拍摄时间，或视情况改拍棚内套餐。 | J20: 实收尾款
B21: * 加家庭拍摄 | D21: 800元/家庭，多3张精修
B22: * 加拍时长 | D22: 1000元/小时 | J22: 付款日期
B23: * 另加化妆 | D23: 500元/小家庭3人 | F23: * 另加长辈化妆 | H23: 200元/人
B24: * 另加精修 | D24: 100元/张 | F24: * 何时选片 | H24: 拍摄完一周左右 | J24: 付款方式
F26: 客户确认签字
B30: 选片日期 | F30: 选片人 | J30: 选片另加费用
B32: 精修张数 | D32: 张（是否参加点评： 是 / 否 ） | F32: 未修底片 | H32: 张
O33: z
B34: 印刷品 | D34: （颜色、款式、尺寸、照片序号）
B36: 修片要求 | J36: 付款日期
J38: 付款方式
B39: 注： | D39: 由于相框为易碎品，为避免意外，如需发快递只发本市，且24寸以上相框需到店自取。
F40: 客户确认签字

Sheet 所有套餐列表
A1: 2880全家福
A2: 3980全家福
A3: 4480主题定制
A4: 2980个人肖像
A5: 4280个人肖像
A6: 3580闺蜜照
A7: 4880大家庭
A8: 7580大家庭
A9: 婚纱肖像
A10: 3580孕照
A11: 2980儿童肖像
A12: 2480儿童平日
... A38: 其他
